<?xml version="1.0" encoding="UTF-8"?><nfeProc versao="4.00" xmlns="http://www.portalfiscal.inf.br/nfe"><NFe xmlns="http://www.portalfiscal.inf.br/nfe"><infNFe versao="4.00" Id="NFe24241109392341000124550010004082061158497849"><ide><cUF>24</cUF><cNF>15849784</cNF><natOp>VENDA DE MERC. ADQUIRIDA OU RECEBIDA DE TERCEIROS</natOp><mod>55</mod><serie>1</serie><nNF>408206</nNF><dhEmi>2024-11-16T11:13:00-03:00</dhEmi><dhSaiEnt>2024-11-16T11:13:00-03:00</dhSaiEnt><tpNF>1</tpNF><idDest>1</idDest><cMunFG>2408102</cMunFG><tpImp>1</tpImp><tpEmis>1</tpEmis><cDV>9</cDV><tpAmb>1</tpAmb><finNFe>1</finNFe><indFinal>1</indFinal><indPres>3</indPres><procEmi>0</procEmi><verProc>1.3.233.021</verProc></ide><emit><CNPJ>09392341000124</CNPJ><xNome>LAMPADINHA MATERIAIS ELETRICOS LTDA LJ 01</xNome><xFant>LAMPADINHA MATERIAIS ELETRICOS LTDA LJ 01</xFant><enderEmit><xLgr>AVENIDA DAO SILVEIRA</xLgr><nro>3740</nro><xBairro>CANDELARIA</xBairro><cMun>2408102</cMun><xMun>NATAL</xMun><UF>RN</UF><CEP>59066180</CEP><cPais>1058</cPais><xPais>BRASIL</xPais><fone>8436154030</fone></enderEmit><IE>200249622</IE><IM>1054791</IM><CRT>3</CRT></emit><dest><CNPJ>14459637000155</CNPJ><xNome>CONDOMINIO LIVING GARDEN</xNome><enderDest><xLgr>RUA CEARA MIRIM N 1140</xLgr><nro>1140</nro><xBairro>TIROL</xBairro><cMun>2408102</cMun><xMun>NATAL</xMun><UF>RN</UF><CEP>59020240</CEP><cPais>1058</cPais><xPais>BRASIL</xPais><fone>8430866767</fone></enderDest><indIEDest>9</indIEDest><email>livinggardengerencia@gmail.com</email></dest><entrega><CNPJ>14459637000155</CNPJ><xLgr>RUA CEARA MIRIM 1140</xLgr><nro>1140</nro><xBairro>TIROL</xBairro><cMun>2408102</cMun><xMun>NATAL</xMun><UF>RN</UF><CEP>59020240</CEP></entrega><det nItem="1"><prod><cProd>22609</cProd><cEAN>SEM GTIN</cEAN><xProd>CABO DE FORCA PARA MANG. LUMINOSA 2 FIOS</xProd><NCM>85444900</NCM><CEST>1200700</CEST><indEscala>S</indEscala><CFOP>5102</CFOP><uCom>UN</uCom><qCom>20.0000</qCom><vUnCom>12.9000000000</vUnCom><vProd>258.00</vProd><cEANTrib>SEM GTIN</cEANTrib><uTrib>UN</uTrib><qTrib>20.0000</qTrib><vUnTrib>12.9000000000</vUnTrib><indTot>1</indTot><xPed>216103768</xPed><nItemPed>4</nItemPed></prod><imposto><vTotTrib>55.86</vTotTrib><ICMS><ICMS00><orig>0</orig><CST>00</CST><modBC>3</modBC><vBC>258.00</vBC><pICMS>18.0000</pICMS><vICMS>46.44</vICMS></ICMS00></ICMS><IPI><cEnq>999</cEnq><IPITrib><CST>99</CST><vBC>0.00</vBC><pIPI>0.0000</pIPI><vIPI>0.00</vIPI></IPITrib></IPI><PIS><PISAliq><CST>01</CST><vBC>211.56</vBC><pPIS>1.6500</pPIS><vPIS>3.49</vPIS></PISAliq></PIS><COFINS><COFINSAliq><CST>01</CST><vBC>211.56</vBC><pCOFINS>7.6000</pCOFINS><vCOFINS>16.08</vCOFINS></COFINSAliq></COFINS></imposto></det><det nItem="2"><prod><cProd>287</cProd><cEAN>7892171276024</cEAN><xProd>CABO FLEXONAX 2X2,5MM 1KV PRETO</xProd><NCM>85444900</NCM><CEST>1200700</CEST><indEscala>S</indEscala><CFOP>5102</CFOP><uCom>M</uCom><qCom>50.0000</qCom><vUnCom>6.9000000000</vUnCom><vProd>345.00</vProd><cEANTrib>7892171276024</cEANTrib><uTrib>M</uTrib><qTrib>50.0000</qTrib><vUnTrib>6.9000000000</vUnTrib><indTot>1</indTot><xPed>216103768</xPed><nItemPed>5</nItemPed></prod><imposto><vTotTrib>74.69</vTotTrib><ICMS><ICMS00><orig>0</orig><CST>00</CST><modBC>3</modBC><vBC>345.00</vBC><pICMS>18.0000</pICMS><vICMS>62.10</vICMS></ICMS00></ICMS><IPI><cEnq>999</cEnq><IPITrib><CST>99</CST><vBC>0.00</vBC><pIPI>0.0000</pIPI><vIPI>0.00</vIPI></IPITrib></IPI><PIS><PISAliq><CST>01</CST><vBC>282.90</vBC><pPIS>1.6500</pPIS><vPIS>4.67</vPIS></PISAliq></PIS><COFINS><COFINSAliq><CST>01</CST><vBC>282.90</vBC><pCOFINS>7.6000</pCOFINS><vCOFINS>21.50</vCOFINS></COFINSAliq></COFINS></imposto><infAdProd>NAO TROCAMOS CABOS EM REATALHO</infAdProd></det><det nItem="3"><prod><cProd>14072</cProd><cEAN>7891040004416</cEAN><xProd>FITA ISOLANTE 19MMX20MTS SCOTCH PRETA 3M</xProd><NCM>40059190</NCM><CFOP>5102</CFOP><uCom>UN</uCom><qCom>2.0000</qCom><vUnCom>29.3000000000</vUnCom><vProd>58.60</vProd><cEANTrib>7891040004416</cEANTrib><uTrib>UN</uTrib><qTrib>2.0000</qTrib><vUnTrib>29.3000000000</vUnTrib><indTot>1</indTot><xPed>216103768</xPed><nItemPed>6</nItemPed></prod><imposto><vTotTrib>12.69</vTotTrib><ICMS><ICMS00><orig>0</orig><CST>00</CST><modBC>3</modBC><vBC>58.60</vBC><pICMS>18.0000</pICMS><vICMS>10.55</vICMS></ICMS00></ICMS><IPI><cEnq>999</cEnq><IPITrib><CST>99</CST><vBC>0.00</vBC><pIPI>0.0000</pIPI><vIPI>0.00</vIPI></IPITrib></IPI><PIS><PISAliq><CST>01</CST><vBC>48.05</vBC><pPIS>1.6500</pPIS><vPIS>0.79</vPIS></PISAliq></PIS><COFINS><COFINSAliq><CST>01</CST><vBC>48.05</vBC><pCOFINS>7.6000</pCOFINS><vCOFINS>3.65</vCOFINS></COFINSAliq></COFINS></imposto></det><det nItem="4"><prod><cProd>14126</cProd><cEAN>7891040014149</cEAN><xProd>FITA ISOLANTE ALTA TENSAO 19MMX10MTS 3M</xProd><NCM>40059190</NCM><CFOP>5102</CFOP><uCom>UN</uCom><qCom>1.0000</qCom><vUnCom>40.7000000000</vUnCom><vProd>40.70</vProd><cEANTrib>7891040014149</cEANTrib><uTrib>UN</uTrib><qTrib>1.0000</qTrib><vUnTrib>40.7000000000</vUnTrib><indTot>1</indTot><xPed>216103768</xPed><nItemPed>7</nItemPed></prod><imposto><vTotTrib>8.81</vTotTrib><ICMS><ICMS00><orig>0</orig><CST>00</CST><modBC>3</modBC><vBC>40.70</vBC><pICMS>18.0000</pICMS><vICMS>7.33</vICMS></ICMS00></ICMS><IPI><cEnq>999</cEnq><IPITrib><CST>99</CST><vBC>0.00</vBC><pIPI>0.0000</pIPI><vIPI>0.00</vIPI></IPITrib></IPI><PIS><PISAliq><CST>01</CST><vBC>33.37</vBC><pPIS>1.6500</pPIS><vPIS>0.55</vPIS></PISAliq></PIS><COFINS><COFINSAliq><CST>01</CST><vBC>33.37</vBC><pCOFINS>7.6000</pCOFINS><vCOFINS>2.54</vCOFINS></COFINSAliq></COFINS></imposto><infAdProd>PERC.PARC.FCI: 0 - N. FCI: 9DA82125-8F9A-45D8-B345-D4D9D8D6F129</infAdProd></det><det nItem="5"><prod><cProd>13754</cProd><cEAN>7896688180355</cEAN><xProd>MANGUEIRA LUMINOSA LED BRANCA 6500K 220V</xProd><NCM>94054900</NCM><CEST>2112200</CEST><indEscala>S</indEscala><CFOP>5102</CFOP><uCom>MT</uCom><qCom>100.0000</qCom><vUnCom>8.9000000000</vUnCom><vProd>890.00</vProd><cEANTrib>7896688180355</cEANTrib><uTrib>MT</uTrib><qTrib>100.0000</qTrib><vUnTrib>8.9000000000</vUnTrib><indTot>1</indTot><xPed>216103768</xPed><nItemPed>8</nItemPed></prod><imposto><vTotTrib>192.69</vTotTrib><ICMS><ICMS00><orig>0</orig><CST>00</CST><modBC>3</modBC><vBC>890.00</vBC><pICMS>18.0000</pICMS><vICMS>160.20</vICMS></ICMS00></ICMS><IPI><cEnq>999</cEnq><IPITrib><CST>99</CST><vBC>0.00</vBC><pIPI>0.0000</pIPI><vIPI>0.00</vIPI></IPITrib></IPI><PIS><PISAliq><CST>01</CST><vBC>729.80</vBC><pPIS>1.6500</pPIS><vPIS>12.04</vPIS></PISAliq></PIS><COFINS><COFINSAliq><CST>01</CST><vBC>729.80</vBC><pCOFINS>7.6000</pCOFINS><vCOFINS>55.46</vCOFINS></COFINSAliq></COFINS></imposto><infAdProd>A MANGUEIRA DE LED E IDEAL PARA TODO TIPO DE DECORACAO; O PRODUTO MAIS UTILIZADO POR ARQUITETOS E DECORADORES PARA DECORAR CASAS, LOJAS, PREDIOS RESIDENCIAIS E COMERCIO DE TODO O BRASIL. ESTE PRODUTO E RECOMENDADO PARA: FACHADAS DE IMOVEIS, ARVORES, CASAS, LOJAS, MONTAGEM DE PERSONAGENS, VITRINES, ETC.</infAdProd></det><det nItem="6"><prod><cProd>23737</cProd><cEAN>7891435050035</cEAN><xProd>PLUGUE FEMEA 3P 10A PRETO TRAMONTINA</xProd><NCM>85366910</NCM><CEST>1200400</CEST><indEscala>S</indEscala><CFOP>5102</CFOP><uCom>UN</uCom><qCom>2.0000</qCom><vUnCom>5.6000000000</vUnCom><vProd>11.20</vProd><cEANTrib>7891435050035</cEANTrib><uTrib>UN</uTrib><qTrib>2.0000</qTrib><vUnTrib>5.6000000000</vUnTrib><indTot>1</indTot><xPed>216103768</xPed><nItemPed>9</nItemPed></prod><imposto><vTotTrib>2.42</vTotTrib><ICMS><ICMS00><orig>0</orig><CST>00</CST><modBC>3</modBC><vBC>11.20</vBC><pICMS>18.0000</pICMS><vICMS>2.02</vICMS></ICMS00></ICMS><IPI><cEnq>999</cEnq><IPITrib><CST>99</CST><vBC>0.00</vBC><pIPI>0.0000</pIPI><vIPI>0.00</vIPI></IPITrib></IPI><PIS><PISAliq><CST>01</CST><vBC>9.18</vBC><pPIS>1.6500</pPIS><vPIS>0.15</vPIS></PISAliq></PIS><COFINS><COFINSAliq><CST>01</CST><vBC>9.18</vBC><pCOFINS>7.6000</pCOFINS><vCOFINS>0.70</vCOFINS></COFINSAliq></COFINS></imposto><infAdProd>PERC.PARC.FCI: 0 - N. FCI: AFF0E3A0-464E-4683-B5DE-86065467938B</infAdProd></det><det nItem="7"><prod><cProd>24448</cProd><cEAN>7891435049916</cEAN><xProd>PLUGUE MACHO 3P 10A 250V PT TRAMONTINA</xProd><NCM>85366910</NCM><CEST>1200400</CEST><indEscala>S</indEscala><CFOP>5102</CFOP><uCom>UN</uCom><qCom>2.0000</qCom><vUnCom>5.5000000000</vUnCom><vProd>11.00</vProd><cEANTrib>7891435049916</cEANTrib><uTrib>UN</uTrib><qTrib>2.0000</qTrib><vUnTrib>5.5000000000</vUnTrib><indTot>1</indTot><xPed>216103768</xPed><nItemPed>10</nItemPed></prod><imposto><vTotTrib>2.38</vTotTrib><ICMS><ICMS00><orig>0</orig><CST>00</CST><modBC>3</modBC><vBC>11.00</vBC><pICMS>18.0000</pICMS><vICMS>1.98</vICMS></ICMS00></ICMS><IPI><cEnq>999</cEnq><IPITrib><CST>99</CST><vBC>0.00</vBC><pIPI>0.0000</pIPI><vIPI>0.00</vIPI></IPITrib></IPI><PIS><PISAliq><CST>01</CST><vBC>9.02</vBC><pPIS>1.6500</pPIS><vPIS>0.15</vPIS></PISAliq></PIS><COFINS><COFINSAliq><CST>01</CST><vBC>9.02</vBC><pCOFINS>7.6000</pCOFINS><vCOFINS>0.69</vCOFINS></COFINSAliq></COFINS></imposto><infAdProd>PERC.PARC.FCI: 0 - N. FCI: 5B68439F-2B33-4C3D-80E3-9ECA70EB7E43</infAdProd></det><det nItem="8"><prod><cProd>4404</cProd><cEAN>7896688220815</cEAN><xProd>CASCATA C/200LEDS 220V BRANCA NITROLUX</xProd><NCM>94053100</NCM><CFOP>5102</CFOP><uCom>UN</uCom><qCom>3.0000</qCom><vUnCom>72.9000000000</vUnCom><vProd>218.70</vProd><cEANTrib>7896688220815</cEANTrib><uTrib>UN</uTrib><qTrib>3.0000</qTrib><vUnTrib>72.9000000000</vUnTrib><indTot>1</indTot><xPed>216103768</xPed><nItemPed>11</nItemPed></prod><imposto><vTotTrib>47.35</vTotTrib><ICMS><ICMS00><orig>0</orig><CST>00</CST><modBC>3</modBC><vBC>218.70</vBC><pICMS>18.0000</pICMS><vICMS>39.37</vICMS></ICMS00></ICMS><IPI><cEnq>999</cEnq><IPITrib><CST>99</CST><vBC>0.00</vBC><pIPI>0.0000</pIPI><vIPI>0.00</vIPI></IPITrib></IPI><PIS><PISAliq><CST>01</CST><vBC>179.33</vBC><pPIS>1.6500</pPIS><vPIS>2.96</vPIS></PISAliq></PIS><COFINS><COFINSAliq><CST>01</CST><vBC>179.33</vBC><pCOFINS>7.6000</pCOFINS><vCOFINS>13.63</vCOFINS></COFINSAliq></COFINS></imposto></det><total><ICMSTot><vBC>1833.20</vBC><vICMS>329.99</vICMS><vICMSDeson>0.00</vICMSDeson><vFCP>0.00</vFCP><vBCST>0.00</vBCST><vST>0.00</vST><vFCPST>0.00</vFCPST><vFCPSTRet>0.00</vFCPSTRet><vProd>1833.20</vProd><vFrete>0.00</vFrete><vSeg>0.00</vSeg><vDesc>0.00</vDesc><vII>0.00</vII><vIPI>0.00</vIPI><vIPIDevol>0.00</vIPIDevol><vPIS>24.80</vPIS><vCOFINS>114.25</vCOFINS><vOutro>0.00</vOutro><vNF>1833.20</vNF><vTotTrib>396.89</vTotTrib></ICMSTot></total><transp><modFrete>9</modFrete><vol><qVol>1</qVol><nVol>1</nVol><pesoL>32.619</pesoL><pesoB>32.621</pesoB></vol></transp><cobr><fat><nFat>408206</nFat><vOrig>1833.20</vOrig><vLiq>1833.20</vLiq></fat></cobr><pag></pag><infAdic><infCpl>CLIENTE 61304-LIVING GARDEN//MATERIAL SOLICITADO POR SR FERNANDO//ENTREGA NO ENDERECO DA NOTA//VENDEDOR- EDUARDA SILVA DE ABREU//28 DIAS//*CONFERIR A MERCADORIA NO ATO DA ENTREGA, NAO ACEITAMOS RECLAMACOES POSTERIORES*</infCpl></infAdic></infNFe><Signature xmlns="http://www.w3.org/2000/09/xmldsig#"><SignedInfo><CanonicalizationMethod Algorithm="http://www.w3.org/TR/2001/REC-xml-c14n-20010315" /><SignatureMethod Algorithm="http://www.w3.org/2000/09/xmldsig#rsa-sha1" /><Reference URI="#NFe24241109392341000124550010004082061158497849"><Transforms><Transform Algorithm="http://www.w3.org/2000/09/xmldsig#enveloped-signature" /><Transform Algorithm="http://www.w3.org/TR/2001/REC-xml-c14n-20010315" /></Transforms><DigestMethod Algorithm="http://www.w3.org/2000/09/xmldsig#sha1" /><DigestValue>X2gYeE5ibqYXfinZlhoItVvAzQc=</DigestValue></Reference></SignedInfo><SignatureValue>DuIQ3tSuD0UyvvEX5lrlYdqqHR8QRa0UG3XZGWlKsZtOSctFtCQ2s+4G74vuNsoc0oiVRFoUAcLrsBUGht1lr/9A+dOi1zeBImv0Ooi7H2sazdXGZzCRJ7Cb/UUP+eCyEWyReG1CDwIPVR6P+UCd6skyZavnWno4U1ADKJ5XGrI=</SignatureValue><KeyInfo><X509Data><X509Certificate>MIICOTCCAaKgAwIBAgIQUXn+h7UWga1DGzpPjVYJZDANBgkqhkiG9w0BAQUFADBbMVkwVwYDVQQDHlAAdwB3AHcALgBmAHMAaQBzAHQALgBjAG8AbQAuAGIAcgAgACgAUwBFAE0AIABWAEEATABJAEQAQQBEAEUAIABKAFUAUgDNAEQASQBDAEEAKTAeFw0yMDA4MTkwOTI3MDZaFw0yMzA4MTkwOTI3MDZaMFsxWTBXBgNVBAMeUAB3AHcAdwAuAGYAcwBpAHMAdAAuAGMAbwBtAC4AYgByACAAKABTAEUATQAgAFYAQQBMAEkARABBAEQARQAgAEoAVQBSAM0ARABJAEMAQQApMIGfMA0GCSqGSIb3DQEBAQUAA4GNADCBiQKBgQDVuzPKD5jupb87mp0A11qpowBTokuORSdopo6YbwvK9eyM0wi3P0qu1UuuVLSQTnHiKMdWEoEWvBmvMYKXpfvQWgAoyJb+IfI21edIrs/UjRxzaBsq8Ui/J9EAcACt60nAFmWMS3U/ZqIqxmv5VDyb+DE/DU9ZOlQ+KnWcE3o7vQIDAQABMA0GCSqGSIb3DQEBBQUAA4GBABV4U5v2ZnFKblaCRGWLZp/jaupbYpzHyYLSl7ur/7eLYH8vpK9JPKcnLekNvbrT224FuBfo1tRHV3vAH+lAWQKwsLNJByRHH4/5LmYVzIZCWLwWRUapANeouRYSGY7Ye9RuCK1T2I1RmrIBaG7uNFT+d9BXA/+bKcJ5hjYShOs8</X509Certificate></X509Data></KeyInfo></Signature></NFe><protNFe versao="4.00"><infProt><tpAmb>1</tpAmb><verAplic>1.3.233.021</verAplic><chNFe>24241109392341000124550010004082061158497849</chNFe><dhRecbto>2024-11-16T11:14:02-03:00</dhRecbto><nProt>224240018810261</nProt><digVal>t3qZZ5Gynpcd2rzF/+d76rT2RWw=</digVal><cStat>100</cStat><xMotivo>Autorizado o uso da NF-e</xMotivo></infProt></protNFe></nfeProc>
